LICENSE.rst
MANIFEST.in
README.rst
setup.cfg
setup.py
dtool_symlink/__init__.py
dtool_symlink/storagebroker.py
dtool_symlink.egg-info/PKG-INFO
dtool_symlink.egg-info/SOURCES.txt
dtool_symlink.egg-info/dependency_links.txt
dtool_symlink.egg-info/entry_points.txt
dtool_symlink.egg-info/requires.txt
dtool_symlink.egg-info/top_level.txt