Metadata-Version: 1.1
Name: dtool-symlink
Version: 0.3.1
Summary: Create dataset where data directory is a symlink
Home-page: https://github.com/jic-dtool/dtool-symlink
Author: Tjelvar Olsson
Author-email: tjelvar.olsson@gmail.com
License: MIT
Download-URL: https://github.com/jic-dtool/dtool-symlink/tarball/0.3.1
Platform: UNKNOWN
